oura_contraindications/__init__.py
oura_contraindications/auth.py
oura_contraindications/client.py
oura_contraindications/client_pandas.py
oura_contraindications/converters.py
oura_contraindications/exceptions.py
oura_contraindications/export/__init__.py
oura_contraindications/export/writers.py
oura_contraindications/v2/__init__.py
oura_contraindications/v2/client.py
oura_contraindications/v2/client_pandas.py
oura_contraindications-1.4.3.dist-info/LICENSE
oura_contraindications-1.4.3.dist-info/METADATA
oura_contraindications-1.4.3.dist-info/WHEEL
oura_contraindications-1.4.3.dist-info/top_level.txt
oura_contraindications-1.4.3.dist-info/RECORD
