Metadata-Version: 2.1
Name: oura-contraindications
Version: 1.4.3
Summary: Oura API client for contraindications
Home-page: https://github.com/smonk333/python-ouraring
Author: smonk333
Author-email: smonk3.the.folf@gmail.com
Project-URL: Bug Tracker, https://github.com/smonk333/python-ouraring/issues
Classifier: License :: OSI Approved :: MIT License
Classifier: Operating System :: OS Independent
Classifier: Programming Language :: Python :: 3
Classifier: Programming Language :: Python :: 3.8
Classifier: Programming Language :: Python :: 3.9
Requires-Python: >=3.8
License-File: LICENSE
Requires-Dist: requests-oauthlib
Requires-Dist: pandas
